ehealthkd/__init__.py
ehealthkd/baseline.py
ehealthkd/evaltest.py
ehealthkd/score.py
ehealthkd/submit.py
ehealthkd/tools.py
ehealthkd/utils.py
ehealthkd-0.2.2.dist-info/WHEEL
ehealthkd-0.2.2.dist-info/METADATA
ehealthkd-0.2.2.dist-info/RECORD
