Metadata-Version: 2.1
Name: ehealthkd
Version: 0.2.2
Summary: Evaluation scripts and tools for eHealth-KD
License: MIT
Author: eHealth-KD
Requires-Python: >=3.6,<4.0
Classifier: License :: OSI Approved :: MIT License
Classifier: Programming Language :: Python :: 3
Classifier: Programming Language :: Python :: 3.6
Classifier: Programming Language :: Python :: 3.7
Classifier: Programming Language :: Python :: 3.8
